homemate_bridge/__init__.py
homemate_bridge/__main__.py
homemate_bridge/cli.py
homemate_bridge/devices.json
homemate_bridge/seed_keyfile.py
homemate_bridge/seed_keyfile.py~
homemate_bridge-0.1.1.dist-info/DESCRIPTION.rst
homemate_bridge-0.1.1.dist-info/METADATA
homemate_bridge-0.1.1.dist-info/RECORD
homemate_bridge-0.1.1.dist-info/WHEEL
homemate_bridge-0.1.1.dist-info/entry_points.txt
homemate_bridge-0.1.1.dist-info/metadata.json
homemate_bridge-0.1.1.dist-info/top_level.txt
