Metadata-Version: 2.0
Name: homemate-bridge
Version: 0.1.1
Summary: Orvibo "Homemate" to MQTT bridge
Home-page: https://github.com/insertjokehere/homemate-bridge
Author: Will Hughes
Author-email: will@willhughes.name
License: Apache
Platform: UNKNOWN
Classifier: Development Status :: 3 - Alpha
Classifier: Intended Audience :: Developers
Classifier: License :: OSI Approved :: Apache Software License
Classifier: Operating System :: Unix
Classifier: Operating System :: POSIX
Classifier: Programming Language :: Python
Classifier: Programming Language :: Python :: 2.7
Classifier: Programming Language :: Python :: 3
Classifier: Programming Language :: Python :: 3.3
Classifier: Programming Language :: Python :: 3.4
Classifier: Programming Language :: Python :: 3.5
Classifier: Programming Language :: Python :: 3.6
Classifier: Programming Language :: Python :: Implementation :: CPython
Classifier: Programming Language :: Python :: Implementation :: PyPy
Classifier: Topic :: Utilities
Requires-Dist: paho-mqtt
Requires-Dist: cryptography
Requires-Dist: hexdump
Requires-Dist: hassdevice (==0.1.0)
